LICENCE.txt
README.md
setup.cfg
setup.py
Topsis/102003106.py
Topsis_Prabhjot_102003106.egg-info/PKG-INFO
Topsis_Prabhjot_102003106.egg-info/SOURCES.txt
Topsis_Prabhjot_102003106.egg-info/dependency_links.txt
Topsis_Prabhjot_102003106.egg-info/entry_points.txt
Topsis_Prabhjot_102003106.egg-info/requires.txt
Topsis_Prabhjot_102003106.egg-info/top_level.txt