Metadata-Version: 2.1
Name: Topsis-Prabhjot-102003106
Version: 1.1.6
Summary: Topsis Calculation Package
Author: Prabhjot Singh Bhatia
Author-email: <prabh3876@gmail.com>
License: MIT License
Keywords: python,topsis,mcdm
Classifier: Development Status :: 1 - Planning
Classifier: Intended Audience :: Developers
Classifier: Programming Language :: Python :: 3
Classifier: Operating System :: Unix
Classifier: Operating System :: MacOS :: MacOS X
Classifier: Operating System :: Microsoft :: Windows
License-File: LICENCE.txt
